model_alignment/__init__.py
model_alignment/alignable_model_calls.py
model_alignment/labeler.py
model_alignment/labeler_prompt_templates.py
model_alignment/labeler_types.py
model_alignment/model_helper.py
model_alignment/prompts.py
model_alignment/single_run.py
model_alignment/utils.py
model_alignment-0.2.dist-info/LICENSE
model_alignment-0.2.dist-info/METADATA
model_alignment-0.2.dist-info/WHEEL
model_alignment-0.2.dist-info/top_level.txt
model_alignment-0.2.dist-info/RECORD
