Metadata-Version: 2.1
Name: model-alignment
Version: 0.2
Summary: Model Alignment: Aligning prompts to human preferences through natural language feedback
Author: Google, LLC
License: 
Project-URL: Homepage, https://github.com/pair-code/model-alignment
Project-URL: Repository, https://github.com/PAIR-code/model-alignment
Project-URL: Bug Tracker, https://github.com/PAIR-code/model-alignment/issues
Keywords: explainable,explainable artifical intelligence,XAI,natural language processing,artifical intelligence,machine learning,deep learning
Classifier: Intended Audience :: Developers
Classifier: Intended Audience :: Science/Research
Classifier: License :: OSI Approved :: Apache Software License
Classifier: Operating System :: OS Independent
Classifier: Programming Language :: Python :: 3 :: Only
Classifier: Programming Language :: Python :: 3.9
Classifier: Programming Language :: Python :: 3.10
Classifier: Topic :: Scientific/Engineering :: Artificial Intelligence
Requires-Python: >=3.9
License-File: LICENSE
Requires-Dist: google-generativeai >=0.3.0
Requires-Dist: jinja2
Requires-Dist: keras >=3.0.0
Requires-Dist: keras-nlp
Requires-Dist: numpy
Requires-Dist: pandas
Requires-Dist: scikit-learn
Requires-Dist: tqdm
